topsis/__init__.py
topsis/topsis_102203215.py
Topsis_Harsh_102203215-1.4.9.dist-info/LICENSE.txt
Topsis_Harsh_102203215-1.4.9.dist-info/METADATA
Topsis_Harsh_102203215-1.4.9.dist-info/WHEEL
Topsis_Harsh_102203215-1.4.9.dist-info/entry_points.txt
Topsis_Harsh_102203215-1.4.9.dist-info/top_level.txt
Topsis_Harsh_102203215-1.4.9.dist-info/RECORD
