Metadata-Version: 2.1
Name: Topsis-Harsh-102203215
Version: 1.4.9
Summary: A Python package for TOPSIS ranking with CLI support for CSV/Excel files
Author: Harsh Lakyan
Author-email: harshlakyan@gmail.com
License: MIT
Keywords: topsis,multi-criteria decision making,python,pypi,csv,xlsx,cli
Classifier: Development Status :: 5 - Production/Stable
Classifier: Intended Audience :: Developers
Classifier: Intended Audience :: Education
Classifier: License :: OSI Approved :: MIT License
Classifier: Programming Language :: Python :: 3
Classifier: Programming Language :: Python :: 3.6
Classifier: Programming Language :: Python :: 3.7
Classifier: Programming Language :: Python :: 3.8
Classifier: Programming Language :: Python :: 3.9
Classifier: Programming Language :: Python :: 3.10
Classifier: Programming Language :: Python :: 3.11
Classifier: Topic :: Scientific/Engineering
Classifier: Topic :: Software Development :: Libraries :: Python Modules
Requires-Python: >=3.6
License-File: LICENSE.txt
Requires-Dist: numpy>=1.21.0
Requires-Dist: pandas>=1.3.0
